iJustWantTemplating/__init__.py
iJustWantTemplating/custom_asserts.py
iJustWantTemplating/custom_datatypes.py
iJustWantTemplating/custom_errors.py
iJustWantTemplating/iJWT.py
iJustWantTemplating/regex_expressions.py
iJustWantTemplating-2.0.2.dist-info/METADATA
iJustWantTemplating-2.0.2.dist-info/WHEEL
iJustWantTemplating-2.0.2.dist-info/top_level.txt
iJustWantTemplating-2.0.2.dist-info/RECORD
