Metadata-Version: 2.1
Name: iJustWantTemplating
Version: 2.0.2
Summary: A very simplistic templating "language" for quick and easy development of static sites.
Author: Neo Sahadeo
Author-email: 
Keywords: python,templating,static sites,static generation
Classifier: Development Status :: 5 - Production/Stable
Classifier: Intended Audience :: Developers
Classifier: Programming Language :: Python :: 3
Classifier: Operating System :: Unix
